dfplayer_card_manager/__init__.py
dfplayer_card_manager/cli/__init__.py
dfplayer_card_manager/cli/cli.py
dfplayer_card_manager/cli/cli_context.py
dfplayer_card_manager/cli/cli_setup.py
dfplayer_card_manager/cli/printing.py
dfplayer_card_manager/cli/commands/__init__.py
dfplayer_card_manager/cli/commands/check.py
dfplayer_card_manager/cli/commands/clean.py
dfplayer_card_manager/cli/commands/sort.py
dfplayer_card_manager/cli/commands/sync.py
dfplayer_card_manager/config/__init__.py
dfplayer_card_manager/config/config_checker.py
dfplayer_card_manager/config/config_merger.py
dfplayer_card_manager/config/config_reader.py
dfplayer_card_manager/config/configuration.py
dfplayer_card_manager/config/yaml_config.py
dfplayer_card_manager/dfplayer/__init__.py
dfplayer_card_manager/dfplayer/dfplayer_card_content_checker.py
dfplayer_card_manager/dfplayer/dfplayer_card_manager.py
dfplayer_card_manager/dfplayer/dfplayer_card_manager_error.py
dfplayer_card_manager/dfplayer/dfplayer_card_manager_interface.py
dfplayer_card_manager/fat/__init__.py
dfplayer_card_manager/fat/fat_checker.py
dfplayer_card_manager/fat/fat_device_mount.py
dfplayer_card_manager/fat/fat_error.py
dfplayer_card_manager/fat/fat_sorter.py
dfplayer_card_manager/fat/fat_sorter_interface.py
dfplayer_card_manager/logging/__init__.py
dfplayer_card_manager/logging/logger.py
dfplayer_card_manager/logging/logger_interface.py
dfplayer_card_manager/logging/verbosity_level.py
dfplayer_card_manager/mp3/__init__.py
dfplayer_card_manager/mp3/audio_diff_checker.py
dfplayer_card_manager/mp3/audio_diff_checker_interface.py
dfplayer_card_manager/mp3/audio_file_manager.py
dfplayer_card_manager/mp3/audio_file_manager_interface.py
dfplayer_card_manager/mp3/tag_collection.py
dfplayer_card_manager/mp3/tag_error.py
dfplayer_card_manager/os/__init__.py
dfplayer_card_manager/os/file_access.py
dfplayer_card_manager/os/path_sanitizer.py
dfplayer_card_manager/repository/__init__.py
dfplayer_card_manager/repository/compare_result.py
dfplayer_card_manager-0.2.1.dist-info/LICENSE
dfplayer_card_manager-0.2.1.dist-info/METADATA
dfplayer_card_manager-0.2.1.dist-info/WHEEL
dfplayer_card_manager-0.2.1.dist-info/entry_points.txt
dfplayer_card_manager-0.2.1.dist-info/top_level.txt
dfplayer_card_manager-0.2.1.dist-info/RECORD
