Metadata-Version: 2.1
Name: dfplayer-card-manager
Version: 0.2.1
Summary: A package for managing SD cards that are meant to be used in DFROBOT DfPlayer Mini card readers.
Home-page: https://github.com/stevenengland/dfplayer_card_manager
Author: Steven England
Author-email: github@steven-england.info
License: MIT
Platform: UNKNOWN
Requires-Python: >=3.8
License-File: LICENSE
Requires-Dist: FATtools==1.0.42
Requires-Dist: eyed3==0.9.7
Requires-Dist: pyyaml==6.0.2
Requires-Dist: pydantic==2.10.6
Requires-Dist: multipledispatch==1.0.0
Requires-Dist: typer==0.15.1
Requires-Dist: types-PyYAML==6.0.12.20241230
Provides-Extra: dev
Requires-Dist: pytest-timeout==2.3.1; extra == "dev"
Requires-Dist: pytest-mock==3.14.0; extra == "dev"
Requires-Dist: mypy==1.10.0; extra == "dev"
Requires-Dist: pyfakefs==5.7.4; extra == "dev"
Requires-Dist: black==24.4.2; extra == "dev"
Requires-Dist: pytest==8.3.4; extra == "dev"
Requires-Dist: pytest-env==1.1.3; extra == "dev"
Requires-Dist: pytest-cov==5.0.0; extra == "dev"
Requires-Dist: wheel==0.45.1; extra == "dev"
Requires-Dist: pre-commit==4.1.0; extra == "dev"
Requires-Dist: strip-ansi==0.1.1; extra == "dev"
Requires-Dist: twine==6.1.0; extra == "dev"
Requires-Dist: faker==33.1.0; extra == "dev"
Requires-Dist: check-wheel-contents==0.6.1; extra == "dev"
Requires-Dist: wemake-python-styleguide==0.19.2; extra == "dev"
Requires-Dist: mockito==1.5.4; extra == "dev"
Requires-Dist: isort==5.13.2; extra == "dev"
